{
  "stage_instance": {
    "template_name": "Baked_sc3_staging_00",
    "translation": [
      0.0,
      0.0,
      0.0
    ],
    "rotation": [
      1.0,
      0.0,
      0.0,
      0.0
    ],
    "translation_origin": "COM"
  },
  "default_lighting": "no_lights",
  "navmesh_instance": "Baked_sc3_staging_00",
  "articulated_object_instances": [
    {
      "template_name": "fridge",
      "fixed_base": true,
      "auto_clamp_joint_limits": true,
      "translation_origin": "COM",
      "motion_type": "DYNAMIC",
      "translation": [
        -2.1782121658325195,
        1.01,
        3.6299728393554687
      ],
      "rotation": [
        1,
        0,
        0,
        0
      ]
    },
    {
      "template_name": "kitchen_counter",
      "fixed_base": true,
      "auto_clamp_joint_limits": true,
      "translation_origin": "COM",
      "motion_type": "DYNAMIC",
      "translation": [
        -2,
        0.03,
        1.6346
      ],
      "rotation": [
        1,
        0,
        0,
        0
      ],
      "uniform_scale": 0.98
    },
    {
      "template_name": "kitchenCupboard_01",
      "fixed_base": true,
      "auto_clamp_joint_limits": true,
      "translation_origin": "COM",
      "motion_type": "DYNAMIC",
      "translation": [
        -2.3,
        1.53,
        1.6346
      ],
      "rotation": [
        -0.707,
        0.707,
        0,
        0
      ],
      "uniform_scale": 0.38
    },
    {
      "template_name": "door2",
      "fixed_base": true,
      "auto_clamp_joint_limits": true,
      "translation_origin": "COM",
      "motion_type": "DYNAMIC",
      "translation": [
        -0.35,
        2.4,
        -2.65
      ],
      "rotation": [
        1,
        0,
        0,
        0
      ]
    },
    {
      "template_name": "cabinet",
      "fixed_base": true,
      "auto_clamp_joint_limits": true,
      "translation_origin": "COM",
      "motion_type": "DYNAMIC",
      "translation": [
        1.1795034408569336,
        0.05,
        7.801118850708008
      ],
      "rotation": [
        0.0007283607869157826,
        -2.1155740459000233e-08,
        0.9999997347452146,
        2.5288107063925475e-07
      ]
    },
    {
      "template_name": "chestOfDrawers_01",
      "fixed_base": true,
      "auto_clamp_joint_limits": true,
      "translation_origin": "COM",
      "motion_type": "DYNAMIC",
      "translation": [
        -2.3432960510253906,
        0.0,
        -0.3921307623386383
      ],
      "rotation": [
        0.7070818793695812,
        -0.7070816475619124,
        -0.005948058348433559,
        -0.005948121568706916
      ],
      "uniform_scale": 0.4
    }
  ]
}